langproxy/__init__.py
langproxy/session.py
langproxy-0.0.2.dist-info/METADATA
langproxy-0.0.2.dist-info/WHEEL
langproxy-0.0.2.dist-info/top_level.txt
langproxy-0.0.2.dist-info/RECORD
